pyrecist/__init__.py
pyrecist/__main__.py
pyrecist/assessment.py
pyrecist/data.py
pyrecist-0.1.0.dist-info/licenses/LICENSE
tests/__init__.py
tests/test_assessment.py
tests/test_data.py
pyrecist-0.1.0.dist-info/METADATA
pyrecist-0.1.0.dist-info/WHEEL
pyrecist-0.1.0.dist-info/entry_points.txt
pyrecist-0.1.0.dist-info/top_level.txt
pyrecist-0.1.0.dist-info/RECORD
