Metadata-Version: 2.4
Name: pyrecist
Version: 0.1.0
Summary: A package for evaluating RECIST criteria from CSV files
Author-email: Roberto Rojas <roberto.rojas.pi@uchile.cl>
License: MIT
Project-URL: Homepage, https://github.com/robertorojasp06/pyrecist
Requires-Python: >=3.7
License-File: LICENSE
Provides-Extra: dev
Requires-Dist: pytest; extra == "dev"
Dynamic: license-file
